uvicorn/__init__.py
uvicorn/__main__.py
uvicorn/_subprocess.py
uvicorn/_types.py
uvicorn/config.py
uvicorn/importer.py
uvicorn/logging.py
uvicorn/main.py
uvicorn/server.py
uvicorn/workers.py
uvicorn/lifespan/__init__.py
uvicorn/lifespan/off.py
uvicorn/lifespan/on.py
uvicorn/loops/__init__.py
uvicorn/loops/asyncio.py
uvicorn/loops/auto.py
uvicorn/loops/uvloop.py
uvicorn/middleware/__init__.py
uvicorn/middleware/asgi2.py
uvicorn/middleware/message_logger.py
uvicorn/middleware/proxy_headers.py
uvicorn/middleware/wsgi.py
uvicorn/protocols/__init__.py
uvicorn/protocols/utils.py
uvicorn/protocols/http/__init__.py
uvicorn/protocols/http/auto.py
uvicorn/protocols/http/flow_control.py
uvicorn/protocols/http/h11_impl.py
uvicorn/protocols/http/httptools_impl.py
uvicorn/protocols/websockets/__init__.py
uvicorn/protocols/websockets/auto.py
uvicorn/protocols/websockets/websockets_impl.py
uvicorn/protocols/websockets/wsproto_impl.py
uvicorn/supervisors/__init__.py
uvicorn/supervisors/basereload.py
uvicorn/supervisors/multiprocess.py
uvicorn/supervisors/statreload.py
uvicorn/supervisors/watchfilesreload.py
uvicorn/supervisors/watchgodreload.py
uvicorn_tschaume-0.19.1.dist-info/METADATA
uvicorn_tschaume-0.19.1.dist-info/WHEEL
uvicorn_tschaume-0.19.1.dist-info/entry_points.txt
uvicorn_tschaume-0.19.1.dist-info/licenses/LICENSE.md
uvicorn_tschaume-0.19.1.dist-info/RECORD
