Metadata-Version: 2.1
Name: uvicorn-tschaume
Version: 0.19.1
Summary: The lightning-fast ASGI server.
Project-URL: Changelog, https://github.com/encode/uvicorn/blob/master/CHANGELOG.md
Project-URL: Funding, https://github.com/sponsors/encode
Project-URL: Homepage, https://www.uvicorn.org/
Project-URL: Source, https://github.com/encode/uvicorn
Author-email: Tom Christie <tom@tomchristie.com>, Patrick Huck <phuck@lbl.gov>
License-File: LICENSE.md
Classifier: Development Status :: 4 - Beta
Classifier: Environment :: Web Environment
Classifier: Intended Audience :: Developers
Classifier: License :: OSI Approved :: BSD License
Classifier: Operating System :: OS Independent
Classifier: Programming Language :: Python :: 3
Classifier: Programming Language :: Python :: 3.7
Classifier: Programming Language :: Python :: 3.8
Classifier: Programming Language :: Python :: 3.9
Classifier: Programming Language :: Python :: 3.10
Classifier: Programming Language :: Python :: 3.11
Classifier: Programming Language :: Python :: Implementation :: CPython
Classifier: Programming Language :: Python :: Implementation :: PyPy
Classifier: Topic :: Internet :: WWW/HTTP
Requires-Python: >=3.7
Requires-Dist: click>=7.0
Requires-Dist: h11>=0.8
Requires-Dist: typing-extensions; python_version < '3.8'
Provides-Extra: standard
Requires-Dist: colorama>=0.4; sys_platform == 'win32' and extra == 'standard'
Requires-Dist: httptools>=0.5.0; extra == 'standard'
Requires-Dist: python-dotenv>=0.13; extra == 'standard'
Requires-Dist: pyyaml>=5.1; extra == 'standard'
Requires-Dist: uvloop!=0.15.0,!=0.15.1,>=0.14.0; sys_platform != 'win32' and (sys_platform != 'cygwin' and platform_python_implementation != 'PyPy') and extra == 'standard'
Requires-Dist: watchfiles>=0.13; extra == 'standard'
Requires-Dist: websockets>=10.0; extra == 'standard'
